enhanced_aslt/__init__.py
enhanced_aslt/cli.py
enhanced_aslt/enhanced_aslt.py
enhanced_automatic_shifted_log-0.1.0.dist-info/LICENSE
enhanced_automatic_shifted_log-0.1.0.dist-info/METADATA
enhanced_automatic_shifted_log-0.1.0.dist-info/WHEEL
enhanced_automatic_shifted_log-0.1.0.dist-info/top_level.txt
enhanced_automatic_shifted_log-0.1.0.dist-info/RECORD
